dialnexa/__init__.py
dialnexa/agents.py
dialnexa/batch_calls.py
dialnexa/calls.py
dialnexa/client.py
dialnexa/http.py
dialnexa/languages.py
dialnexa/llms.py
dialnexa/voices.py
dialnexa-0.1.1.dist-info/METADATA
dialnexa-0.1.1.dist-info/WHEEL
dialnexa-0.1.1.dist-info/top_level.txt
dialnexa-0.1.1.dist-info/RECORD
