Metadata-Version: 2.4
Name: dialnexa
Version: 0.1.1
Summary: DialNexa Python SDK
Author-email: DialNexa <dev@dialnexa.com>
License: MIT
Project-URL: Homepage, https://dialnexa.com
Project-URL: Repository, https://github.com/dialnexa/python-sdk
Requires-Python: >=3.8
Requires-Dist: requests>=2.31.0
Requires-Dist: typing-extensions>=4.7; python_version < "3.11"
Requires-Dist: python-dotenv>=1.0.0
